{
  "kind": "collectionType",
  "collectionName": "events",
  "info": {
    "singularName": "event",
    "pluralName": "events",
    "displayName": "Event",
    "description": ""
  },
  "options": {
    "draftAndPublish": true
  },
  "pluginOptions": {
    "i18n": {
      "localized": true
    }
  },
  "attributes": {
    "image": {
      "type": "media",
      "multiple": false,
      "required": false,
      "allowedTypes": [
        "images",
        "files",
        "videos",
        "audios"
      ],
      "pluginOptions": {
        "i18n": {
          "localized": true
        }
      }
    },
    "imageAlt": {
      "pluginOptions": {
        "i18n": {
          "localized": true
        }
      },
      "type": "string"
    },
    "eventDate": {
      "pluginOptions": {
        "i18n": {
          "localized": true
        }
      },
      "type": "date"
    },
    "eventTime": {
      "pluginOptions": {
        "i18n": {
          "localized": true
        }
      },
      "type": "time"
    },
    "eventPlace": {
      "pluginOptions": {
        "i18n": {
          "localized": true
        }
      },
      "type": "string"
    },
    "title": {
      "pluginOptions": {
        "i18n": {
          "localized": true
        }
      },
      "type": "string"
    },
    "description": {
      "pluginOptions": {
        "i18n": {
          "localized": true
        }
      },
      "type": "text"
    },
    "slug": {
      "pluginOptions": {
        "i18n": {
          "localized": true
        }
      },
      "type": "uid",
      "targetField": "title"
    }
  }
}
